fastclimate/__init__.py
fastclimate/_nbdev.py
fastclimate/core.py
fastclimate/data.py
fastclimate-0.0.1.dist-info/LICENSE
fastclimate-0.0.1.dist-info/METADATA
fastclimate-0.0.1.dist-info/WHEEL
fastclimate-0.0.1.dist-info/entry_points.txt
fastclimate-0.0.1.dist-info/top_level.txt
fastclimate-0.0.1.dist-info/RECORD
